{
  "name": "Alappuzha Gymkhana (2025) Hindi Malayalam 720p WEBRip x264 ESub [DDN].mp4",
  "path": "D:\\Alappuzha Gymkhana (2025) Hindi Malayalam 720p WEBRip x264 ESub [DDN].mp4",
  "uploaded_at": "2026-04-23T22:36:30Z",
  "remote_folder_id": 1751859,
  "mediatype": "video",
  "stream_link": "https://cloud.jazzdrive.com.pk/ui/html/video.html?id=241995732",
  "tmdb": {
    "tmdb_id": 1245571,
    "title": "Alappuzha Gymkhana",
    "original_title": "\u0d06\u0d32\u0d2a\u0d4d\u0d2a\u0d41\u0d34 \u0d1c\u0d3f\u0d02\u0d16\u0d3e\u0d28",
    "release_date": "2025-04-10",
    "year": "2025",
    "rating": 6.538,
    "overview": "A group of youngsters, after failing their plus two exams, aims to join a common college through the sports quota. They choose boxing as their sport. By luck, they manage to survive the district-level competitions. But what will happen at the higher levels?",
    "poster_path": "https://image.tmdb.org/t/p/w500/q4OwzcY6r2L1M1S6uYzmtzjwAqX.jpg",
    "backdrop_path": "https://image.tmdb.org/t/p/original/gndCUsT53TIykPAG393UqgjU69T.jpg",
    "genre_ids": [
      28,
      18,
      35
    ]
  },
  "response": {
    "success": "Media uploaded successfully",
    "id": "241995732",
    "status": "U",
    "etag": "aqUlRS0fkL8XSWRhsd6UUA==",
    "metadata": {
      "mediaserverurl": "https://cloud.jazzdrive.com.pk",
      "videos": [
        {
          "id": "241995732",
          "url": "/sapi/download/video?action=get&k=KjIYtK0kqVIwUEAuShAiRon9uX9rrNXmpN-Tc9QbWy2th8ytKZW2kyxMBrKVlO0yPQs2Cz3mDNDehY7XaRji1N7A5FbM2cUus2-3EqnyU9oyCLPkXj6qZg1OBLj8dUCLZjbjafWUs4oPas7HTLDGeRO7ZlzRJEb6uggMkdfp_LN4sjOaAGs&node=2i182",
          "viewurl": "/sapi/download/video?action=get&k=jV_WGFAtByxxxNveFXfSVbjYIyLhdnJphnrWiiEIctB06CHES5LHoBIOfBtp2BjDOJWtFdQHKGlr0kwfp7JuEnQ56aUIoyLUJHqJeYc8f9ayZTK7_FKvOdvjn2RbkihMA2r6Oniqehjas93VHPY8xhh87_Xhim_WnPshaFDE5WoXy-xSRSDCnLwSv1atyx3QAjQ&node=2i182",
          "date": 1776983789863,
          "creationdate": 1776983451000,
          "modificationdate": 1776983451000,
          "uploaded": 1776983728125,
          "size": 1551930812,
          "name": "Alappuzha Gymkhana (2025) Hindi Malayalam 720p WEBRip x264 ESub [DDN].mp4",
          "metadata": {
            "duration": 8357748,
            "bitrate": 1485501,
            "codec": "h264",
            "height": 544,
            "width": 1280,
            "audiocodec": "aac"
          },
          "playbackurl": "",
          "transcodingstatus": "E",
          "thumbnails": [
            {
              "w": 256,
              "h": 108,
              "size": "176",
              "url": "/sapi/download/video?action=get&k=iUCL8EZEB-nWzX0H8fAeou3-rFfbxQdkINy1Jxjs2mvfzmJDO_cKYbQDqUKllN43aW4N0pqSkVQDDr-yMgXhtwhczpBDKngV0crfPFS0HboMB27pay9wS7WegRop-gKGdX-B88dwMef3lendLy9aoSHYra-lROP4m6BIbNYPulOiAvqv1jayLXor_vsXNfg9OrY&node=2i182",
              "etag": "0aqUlRS0fkL8XSWRhsd6UUA=="
            },
            {
              "w": 1024,
              "h": 435,
              "size": "504",
              "url": "/sapi/download/video?action=get&k=jV_WGFAtByxxxNveFXfSVbjYIyLhdnJphnrWiiEIctB06CHES5LHoBIOfBtp2BjDOJWtFdQHKGlr0kwfp7JuEnQ56aUIoyLUJHqJeYc8f9ayZTK7_FKvOdvjn2RbkihMA2r6Oniqehjas93VHPY8xhh87_Xhim_WnPshaFDE5WoXy-xSRSDCnLwSv1atyx3QAjQ&node=2i182",
              "etag": "0aqUlRS0fkL8XSWRhsd6UUA=="
            }
          ],
          "mediatype": "video",
          "status": "U",
          "etag": "aqUlRS0fkL8XSWRhsd6UUA==",
          "favorite": false
        }
      ]
    },
    "responsetime": 1776983789970,
    "type": "video"
  },
  "share_url": "https://cloud.jazzdrive.com.pk/share/f/48jq7oQDTcuLeG8uWUcVWjMxNTY4NDA4ODI3NzFfMjYxNDMxNQ",
  "share_key": "",
  "share_folder_id": "",
  "share_folder_path": "Alappuzha Gymkhana (2025)",
  "media_kind": "movie"
}