{
  "name": "Su From So (2025) Kannada 720p WEBRip x264 ESub [DDN].mp4",
  "path": "D:\\New folder\\Su From So (2025) Kannada 720p WEBRip x264 ESub [DDN].mp4",
  "uploaded_at": "2026-04-24T17:37:05Z",
  "remote_folder_id": 1752302,
  "mediatype": "video",
  "stream_link": "https://cloud.jazzdrive.com.pk/ui/html/video.html?id=242002117",
  "tmdb": {
    "tmdb_id": 1513656,
    "title": "Su from So",
    "original_title": "\u0cb8\u0cc1 \u0cab\u0ccd\u0cb0\u0cae\u0ccd \u0cb8\u0cca",
    "release_date": "2025-07-25",
    "year": "2025",
    "rating": 7.389,
    "overview": "In a peaceful village full of joy, laughter, and vibrant life, everything seems perfect\u2014until one day, the devil arrives. What follows is a hilarious chain of events that flips the entire village upside down!",
    "poster_path": "https://image.tmdb.org/t/p/w500/a9v6QSFClDqGX2D0YCORp8T1Ji0.jpg",
    "backdrop_path": "https://image.tmdb.org/t/p/original/fBnwpACxGkChCTVvWSfwjeKbSPv.jpg",
    "genre_ids": [
      35,
      27
    ]
  },
  "response": {
    "success": "Media uploaded successfully",
    "id": "242002117",
    "status": "U",
    "etag": "7Vp8HiZE3RQaT2Bi4W/i8g==",
    "metadata": {
      "mediaserverurl": "https://cloud.jazzdrive.com.pk",
      "videos": [
        {
          "id": "242002117",
          "url": "/sapi/download/video?action=get&k=XwYMlos-9mec-bQStVsJDhlB9MU5Asz4cV9WTM7_nQRs3tKEk0xkycplRrPFgThyvod6Ym9Xu51-6xrEvXeqWDCDm3Cid3WhTFhWFD4AfKB8qqJqygx4GAqEm3mdAS5BuZf7cUQ89WHQ7wAIOzxo7zwIK9Ax_CfmT8Aihb1gp5BJLjnZDwQ&node=1i220",
          "viewurl": "/sapi/download/video?action=get&k=3ci0rE4zKlyO49FruhYTJFRh1gcVTpSrkntCBO6DVfBxJKfIzDNLYg0CbHynBK0plU7-jdIDz3O1d6F3Z6ZZOorLF-1k-YyaBpqDKq8zf5M7qa-Cm3QMpw98VVz8kXM4m7bky2k6HmAJqUdWZvqQCQmpFRUgsmuJRVtnHmwDVkHd1AxD16UiZsVf4igkHPGmCyM&node=1i220",
          "date": 1777052224688,
          "creationdate": 1777052019000,
          "modificationdate": 1777052019000,
          "uploaded": 1777052159925,
          "size": 1185241882,
          "name": "Su From So (2025) Kannada 720p WEBRip x264 ESub [DDN].mp4",
          "metadata": {
            "duration": 7836065,
            "bitrate": 1210037,
            "codec": "h264",
            "height": 536,
            "width": 1280,
            "audiocodec": "aac"
          },
          "playbackurl": "",
          "transcodingstatus": "E",
          "thumbnails": [
            {
              "w": 256,
              "h": 107,
              "size": "176",
              "url": "/sapi/download/video?action=get&k=tDUJwLaxva_zobMY7AIUxZExPM5gfj6XhMasAt-YeMcoTQE-9OUw7fkCaYTONJdrTAEkrkTDEefbVvBIu2p8DZEvCA_aDrrNdcNq84TYR8ldVC3--5Vn1Dk1160Q7TYMuojeVBQIrBviZubk87AZ_2dj0pbBoUd1ZICzr5a1QxusDWgdlEGn-wL4tvx6QSzc6dQ&node=1i220",
              "etag": "07Vp8HiZE3RQaT2Bi4W/i8g=="
            },
            {
              "w": 1024,
              "h": 428,
              "size": "504",
              "url": "/sapi/download/video?action=get&k=3ci0rE4zKlyO49FruhYTJFRh1gcVTpSrkntCBO6DVfBxJKfIzDNLYg0CbHynBK0plU7-jdIDz3O1d6F3Z6ZZOorLF-1k-YyaBpqDKq8zf5M7qa-Cm3QMpw98VVz8kXM4m7bky2k6HmAJqUdWZvqQCQmpFRUgsmuJRVtnHmwDVkHd1AxD16UiZsVf4igkHPGmCyM&node=1i220",
              "etag": "07Vp8HiZE3RQaT2Bi4W/i8g=="
            }
          ],
          "mediatype": "video",
          "status": "U",
          "etag": "7Vp8HiZE3RQaT2Bi4W/i8g==",
          "favorite": false
        }
      ]
    },
    "responsetime": 1777052224760,
    "type": "video"
  },
  "share_url": "https://cloud.jazzdrive.com.pk/share/f/0RHpBfkCTUyE-6sEwA-ZXTMxNTY4NDA4ODI3NzFfMjYxNDMxNQ",
  "share_key": "",
  "share_folder_id": "",
  "share_folder_path": "Su From So (2025)",
  "media_kind": "movie"
}