{
  "name": "Nishaanchi 2 (2025) Hindi 720p WEBRip x264 ESub [DDN].mp4",
  "path": "D:\\New folder\\Nishaanchi 2 (2025) Hindi 720p WEBRip x264 ESub [DDN].mp4",
  "uploaded_at": "2026-04-25T19:29:01Z",
  "remote_folder_id": 1752555,
  "mediatype": "video",
  "stream_link": "https://cloud.jazzdrive.com.pk/ui/html/video.html?id=242013816",
  "tmdb": {
    "tmdb_id": 1580286,
    "title": "Nishaanchi 2",
    "original_title": "\u0928\u093f\u0936\u093e\u0902\u091a\u0940 - \u092d\u093e\u0917 \u0968",
    "release_date": "2025-11-14",
    "year": "2025",
    "rating": 5.8,
    "overview": "After another stint in jail, Tony finds that Rinku, his one true love and hope, has been taken by his brother Dabloo. This shocks him into reforming, but Ambika drags him back into crime, with Kamal on his trail. How Manjari gets to have the last laugh, with Tony, Ambika and Kamal at the forefront, forms the rest of the two-part gangster drama.",
    "poster_path": "https://image.tmdb.org/t/p/w500/xUayFrF27SdDZYlKQBUlqxUOxcB.jpg",
    "backdrop_path": "https://image.tmdb.org/t/p/original/tgxZsXnWkoPWQcrGLk6GYwwgSKX.jpg",
    "genre_ids": [
      18,
      80
    ]
  },
  "response": {
    "success": "Media uploaded successfully",
    "id": "242013816",
    "status": "U",
    "etag": "dGhU2gSp0KvEUMFcsOiJIw==",
    "metadata": {
      "mediaserverurl": "https://cloud.jazzdrive.com.pk",
      "videos": [
        {
          "id": "242013816",
          "url": "/sapi/download/video?action=get&k=lDlZMR_38GK8bwuXQ_8LEYbr6K9K3c11EfTbKjbUxaV9YllenwLEbjLFRtxMLWLSjZMVwRlIUBaBfm3xCPsfI4pc-tTxJ4okjZfRuBn1o9x7_8EoR6NAYBO_V82X2YfrNfw0QGTpLIQ-TNbtLWY4tRBA0Qr0AnDaMdiy6G9PtVtMHOIPn4Y&node=1i220",
          "viewurl": "/sapi/download/video?action=get&k=aExdUfJTBLrJ-UwatpkRTdZ7uCWWOYxLBD150jTntIs5WT7H7q8zTPIBy3tmQZepZi7_ZQXDCr6tLBnsl8J04T_UqIZwLARtY8QyJpJvL-P1fKZ5wedpUkSpiWpuEx28vApJvBGyMDVcC_LNhYklsSMLUFDbYuivgUW1JiAhA01nQ9-ylXqpmZ144AJ0d_4rfIg&node=1i220",
          "date": 1777145340835,
          "creationdate": 1777145042000,
          "modificationdate": 1777145042000,
          "uploaded": 1777145295414,
          "size": 1405513486,
          "name": "Nishaanchi 2 (2025) Hindi 720p WEBRip x264 ESub [DDN].mp4",
          "metadata": {
            "duration": 8784272,
            "bitrate": 1280027,
            "codec": "h264",
            "height": 544,
            "width": 1280,
            "audiocodec": "aac"
          },
          "playbackurl": "",
          "transcodingstatus": "E",
          "thumbnails": [
            {
              "w": 256,
              "h": 108,
              "size": "176",
              "url": "/sapi/download/video?action=get&k=p6nNq0LRDNMmaisqhJm18Ioh8tv0ltsssfiL3e8obHGEeQ0VOoVIdvVN3t8XdnPuBiaXf_JrhfeI7S_0WwB_rHmUL_55NrUkEpn6IXh7OZqQpDFYvxKnp44U9S3yD2IdGYFheNevlG6DDoV8SslBmZ4vjvvK-16XeotNPwjT-X0HIjuObhccrRxYmore1HnowH0&node=1i220",
              "etag": "0dGhU2gSp0KvEUMFcsOiJIw=="
            },
            {
              "w": 1024,
              "h": 435,
              "size": "504",
              "url": "/sapi/download/video?action=get&k=aExdUfJTBLrJ-UwatpkRTdZ7uCWWOYxLBD150jTntIs5WT7H7q8zTPIBy3tmQZepZi7_ZQXDCr6tLBnsl8J04T_UqIZwLARtY8QyJpJvL-P1fKZ5wedpUkSpiWpuEx28vApJvBGyMDVcC_LNhYklsSMLUFDbYuivgUW1JiAhA01nQ9-ylXqpmZ144AJ0d_4rfIg&node=1i220",
              "etag": "0dGhU2gSp0KvEUMFcsOiJIw=="
            }
          ],
          "mediatype": "video",
          "status": "U",
          "etag": "dGhU2gSp0KvEUMFcsOiJIw==",
          "favorite": false
        }
      ]
    },
    "responsetime": 1777145340894,
    "type": "video"
  },
  "share_url": "https://cloud.jazzdrive.com.pk/share/f/eny93HZxSe2ROT6cxtF-ujMxNTY4NDA4ODI3NzFfMjYxNDMxNQ",
  "share_key": "",
  "share_folder_id": "",
  "share_folder_path": "Nishaanchi 2 (2025)",
  "media_kind": "movie"
}