{
  "name": "Pogumidam Vegu Thooramillai (2024) Hindi Tamil 720p WEBRip x264 ESub [DDN].mp4",
  "path": "D:\\New folder\\Pogumidam Vegu Thooramillai (2024) Hindi Tamil 720p WEBRip x264 ESub [DDN].mp4",
  "uploaded_at": "2026-04-24T16:30:46Z",
  "remote_folder_id": 1752236,
  "mediatype": "video",
  "stream_link": "https://cloud.jazzdrive.com.pk/ui/html/video.html?id=242001656",
  "tmdb": {
    "tmdb_id": 1329956,
    "title": "Pogumidam Vegu Thooramillai",
    "original_title": "\u0baa\u0bcb\u0b95\u0bc1\u0bae\u0bbf\u0b9f\u0bae\u0bcd \u0bb5\u0bc6\u0b95\u0bc1\u0ba4\u0bc2\u0bb0\u0bae\u0bbf\u0bb2\u0bcd\u0bb2\u0bc8",
    "release_date": "2024-08-23",
    "year": "2024",
    "rating": 7.0,
    "overview": "A mortuary driver's life embarks on a lengthy expedition to transport a deceased individual who is the pride and honour of two feuding families.",
    "poster_path": "https://image.tmdb.org/t/p/w500/t9PskkYrJpFsS2eobDHwNl39T1J.jpg",
    "backdrop_path": "https://image.tmdb.org/t/p/original/isk42t2VOvQF5qQYpDEEqEehRP6.jpg",
    "genre_ids": [
      53,
      10751,
      18
    ]
  },
  "response": {
    "success": "Media uploaded successfully",
    "id": "242001656",
    "status": "U",
    "etag": "T/zpqWfIpOVgovbKvx17/g==",
    "metadata": {
      "mediaserverurl": "https://cloud.jazzdrive.com.pk",
      "videos": [
        {
          "id": "242001656",
          "url": "/sapi/download/video?action=get&k=7QF3URQViJ_OznhghYR2oHfYQFyoi-bmezU-h31INr7QLDlS6DcbTm0zUpU7K0znJOdEMvmzlp9QRejD13h5zB0epuINkxSWamCAV7RjfauqwyJ8uREQs6QdIpagwcRGV2sgfULm-k3uVYVPCqvag5kAMsWyY5ZBzvjmr61T2eiAce6i0Ew&node=1i220",
          "viewurl": "/sapi/download/video?action=get&k=7QXTgEvj6G5nxhCluWLqXjFx-l08pSPcPeMKU2l9gHH62r4kjsgXLKouUg2MutVY3w1asBx6QkUQZJbfWLvtCebCraoc-ONpUhUAqHI0ntuY9a_dP-wze9NrDSEJFjnmIO2p-7vLshgiOsYJB8363IDyBKM4QMam3dWNIR8bcL4aNfTRoonkpdU5pMzb0iXBR8Q&node=1i220",
          "date": 1777048245964,
          "creationdate": 1777047939000,
          "modificationdate": 1777047939000,
          "uploaded": 1777048196009,
          "size": 1475294473,
          "name": "Pogumidam Vegu Thooramillai (2024) Hindi Tamil 720p WEBRip x264 ESub [DDN].mp4",
          "metadata": {
            "duration": 7940745,
            "bitrate": 1486303,
            "codec": "h264",
            "height": 528,
            "width": 1280,
            "audiocodec": "aac"
          },
          "playbackurl": "",
          "transcodingstatus": "E",
          "thumbnails": [
            {
              "w": 256,
              "h": 105,
              "size": "176",
              "url": "/sapi/download/video?action=get&k=GuvnfuiurtAnnHw7dYsZj6Ycdl1g8StXMqaZxoqHKJIQs5yHrzbQFF0dQQYWExXJLBqTu86Cs193KJuIJoGk6W34ZA2SaodzqO4lMBdV_DSTWZbk_XACMnRlxuGulGJhYOd-8czYGuNzjtAEDo1mY0JfMgZZcIuv5D4TFpnA15gc2ySQj1N1WfPMVO7dAie072o&node=1i220",
              "etag": "0T/zpqWfIpOVgovbKvx17/g=="
            },
            {
              "w": 1024,
              "h": 422,
              "size": "504",
              "url": "/sapi/download/video?action=get&k=7QXTgEvj6G5nxhCluWLqXjFx-l08pSPcPeMKU2l9gHH62r4kjsgXLKouUg2MutVY3w1asBx6QkUQZJbfWLvtCebCraoc-ONpUhUAqHI0ntuY9a_dP-wze9NrDSEJFjnmIO2p-7vLshgiOsYJB8363IDyBKM4QMam3dWNIR8bcL4aNfTRoonkpdU5pMzb0iXBR8Q&node=1i220",
              "etag": "0T/zpqWfIpOVgovbKvx17/g=="
            }
          ],
          "mediatype": "video",
          "status": "U",
          "etag": "T/zpqWfIpOVgovbKvx17/g==",
          "favorite": false
        }
      ]
    },
    "responsetime": 1777048246029,
    "type": "video"
  },
  "share_url": "https://cloud.jazzdrive.com.pk/share/f/bWTcKo5uRIKKSWY-dlzvHzMxNTY4NDA4ODI3NzFfMjYxNDMxNQ",
  "share_key": "",
  "share_folder_id": "",
  "share_folder_path": "Pogumidam Vegu Thooramillai (2024)",
  "media_kind": "movie"
}