{
  "name": "Ulajh (2024) Hindi 720p WEBRip x264 ESub [DDN].mp4",
  "path": "D:\\New folder\\Ulajh (2024) Hindi 720p WEBRip x264 ESub [DDN].mp4",
  "uploaded_at": "2026-04-25T20:30:58Z",
  "remote_folder_id": 1752592,
  "mediatype": "video",
  "stream_link": "https://cloud.jazzdrive.com.pk/ui/html/video.html?id=242013879",
  "tmdb": {
    "tmdb_id": 1124876,
    "title": "Ulajh",
    "original_title": "Ulajh",
    "release_date": "2024-08-02",
    "year": "2024",
    "rating": 5.429,
    "overview": "The journey of a young IFS officer, belonging to a prominent family of patriots, who gets embroiled in a dangerous personal conspiracy while far from her home turf, at a career-defining post.",
    "poster_path": "https://image.tmdb.org/t/p/w500/tRTaE89m8As6G6aqgYjCBmm6MKN.jpg",
    "backdrop_path": "https://image.tmdb.org/t/p/original/gOvb0MWKeg97AWr7Cpvi3aDnB0r.jpg",
    "genre_ids": [
      18,
      53
    ]
  },
  "response": {
    "success": "Media uploaded successfully",
    "id": "242013879",
    "status": "U",
    "etag": "WzZZq5FIKWv6QSIx4gdgJg==",
    "metadata": {
      "mediaserverurl": "https://cloud.jazzdrive.com.pk",
      "videos": [
        {
          "id": "242013879",
          "url": "/sapi/download/video?action=get&k=mP9lLO00pv6gogaRirgx1TtoZhFQ7puNshwclDiM9gU7Be_uVkIeQLOb7AvDzY99CuOGevAd7A15r_FSPVW6jyLEhgFsufcyheyLJXqrPBZD9d9t0tupkdek0qW9sx2I-beJlczv7JM4dduivngHropvMXB_MjYZM89kn7qZIJ7lTBBR5hM&node=1i220",
          "viewurl": "/sapi/download/video?action=get&k=WgUMqiwkvcTFNu49RUGmnlbize18tVr_xD-Ors8CjTRtgZkalQjmsvzRxgZh4eonhTHThw6kQJpDYxPrVbW54AJYlVsiHYuchnCNyRvJn1xxUv-QMiRn1v2vspqa-uVZr2ehIUjVuWPClA9lAHzrH4uVnKZYpt4msSKGznbzCXBUvWV3wrpPVzP01Eoa4Z_GerI&node=1i220",
          "date": 1777149057634,
          "creationdate": 1777148792000,
          "modificationdate": 1777148792000,
          "uploaded": 1777149012763,
          "size": 1235220315,
          "name": "Ulajh (2024) Hindi 720p WEBRip x264 ESub [DDN].mp4",
          "metadata": {
            "duration": 7724502,
            "bitrate": 1279275,
            "codec": "h264",
            "height": 720,
            "width": 1280,
            "audiocodec": "aac"
          },
          "playbackurl": "",
          "transcodingstatus": "E",
          "thumbnails": [
            {
              "w": 256,
              "h": 144,
              "size": "176",
              "url": "/sapi/download/video?action=get&k=1m565uP619crJUvGPi3-l8Oxy5tDL1jSlhM-IMPp96e7YRsLDOZyVQSo-GamXm3u2A5QCG7hy9KApKoj9hCSu40k7IIAKfdf9XEhSFkqBSRRHe96HR3qXsV_yvVJ-2ynkMR0vXYsswQib4NFUokHBdx8NaGIMcG4ctnQzrGqWJPXk8Mv1lw9pslJENfz2pmrkiM&node=1i220",
              "etag": "0WzZZq5FIKWv6QSIx4gdgJg=="
            },
            {
              "w": 1024,
              "h": 576,
              "size": "504",
              "url": "/sapi/download/video?action=get&k=WgUMqiwkvcTFNu49RUGmnlbize18tVr_xD-Ors8CjTRtgZkalQjmsvzRxgZh4eonhTHThw6kQJpDYxPrVbW54AJYlVsiHYuchnCNyRvJn1xxUv-QMiRn1v2vspqa-uVZr2ehIUjVuWPClA9lAHzrH4uVnKZYpt4msSKGznbzCXBUvWV3wrpPVzP01Eoa4Z_GerI&node=1i220",
              "etag": "0WzZZq5FIKWv6QSIx4gdgJg=="
            }
          ],
          "mediatype": "video",
          "status": "U",
          "etag": "WzZZq5FIKWv6QSIx4gdgJg==",
          "favorite": false
        }
      ]
    },
    "responsetime": 1777149057727,
    "type": "video"
  },
  "share_url": "https://cloud.jazzdrive.com.pk/share/f/ICMGo6OSS4-hIWCZNpn8GTMxNTY4NDA4ODI3NzFfMjYxNDMxNQ",
  "share_key": "",
  "share_folder_id": "",
  "share_folder_path": "Ulajh (2024)",
  "media_kind": "movie"
}