{
  "name": "Ki-Mein-Jhoot-Boleya-(2023)-Punjabi-HDRip--480p-[Orgmovies].mp4",
  "path": "D:\\Punjabi\\Ki-Mein-Jhoot-Boleya-(2023)-Punjabi-HDRip--480p-[Orgmovies].mp4",
  "uploaded_at": "2026-05-03T19:10:46Z",
  "remote_folder_id": 1753677,
  "mediatype": "video",
  "stream_link": "https://cloud.jazzdrive.com.pk/ui/html/video.html?id=242124755",
  "tmdb": {
    "tmdb_id": 1104118,
    "title": "Ki Mein Jhoot Boleya",
    "original_title": "Ki Mein Jhoot Boleya",
    "release_date": "2023-03-24",
    "year": "2023",
    "rating": 6.0,
    "overview": "Manvir, a down-on-luck NRI, has to find a job and house to be able to marry his girlfriend. He finds the perfect home, but there's a catch. The owner only allows married couples. What will he do?",
    "poster_path": "https://image.tmdb.org/t/p/w500/WiNbxyHw4pWQKhVl7WudSYdKsX.jpg",
    "backdrop_path": "https://image.tmdb.org/t/p/original/ytvV7XZDCfimjmx5681V2hqsgcl.jpg",
    "genre_ids": [
      10749,
      35
    ]
  },
  "response": {
    "success": "Media uploaded successfully",
    "id": "242124755",
    "status": "U",
    "etag": "eSNGimACUM+JKU1TGqgZRw==",
    "metadata": {
      "mediaserverurl": "https://cloud.jazzdrive.com.pk",
      "videos": [
        {
          "id": "242124755",
          "url": "/sapi/download/video?action=get&k=gD89PYfaQM3KmHdIzQue_b9nuxrVpIcYNTT_hCnPHzl6c5puT9F_bC4U52Uey5f3EK2GPnr1i6k_H1K9FsRMJuqU2txqiXZPeNYhHnnw79YdQErpcKHRhsFloSLYQsmqM1supaHfgCqlXhASKg2_-Skr1ygp2jws28Od8qAMTwq2AWdG6SA&node=1i204",
          "viewurl": "/sapi/download/video?action=get&k=n6Ca8NU0_AP4NMVuTmI0pKFj6XSvjGsX40xY3HI72CsAWOV7M8LWOLw4ItaZqb05ENStnzVVbSM3YCTuv-wMEixMpsAA24N1jRe0FZyzcp6TjNlkbkEVdB8P_EdiEQR1NLLPUehesbokmkvG3WLovklTa2m7yOFQPV8GX_RXC4_KD02zCq3piTZLnl2sMrHkP88&node=1i204",
          "date": 1777835445187,
          "creationdate": 1777835331000,
          "modificationdate": 1777835331000,
          "uploaded": 1777835420953,
          "size": 417318447,
          "name": "Ki-Mein-Jhoot-Boleya-(2023)-Punjabi-HDRip--480p-[Orgmovies].mp4",
          "metadata": {
            "duration": 7905531,
            "bitrate": 422305,
            "codec": "h264",
            "height": 306,
            "width": 720,
            "audiocodec": "mp3"
          },
          "playbackurl": "",
          "transcodingstatus": "E",
          "thumbnails": [
            {
              "w": 256,
              "h": 108,
              "size": "176",
              "url": "/sapi/download/video?action=get&k=CrBgB63spWNFbPN_X7ZW6wb5W2GmymQk7S5eHFyi3iJ6b5KFUa32l6VRp9laToPL5RIFnhSwauT6gwzLiZeeloRV0SPG8aXSTnrUrNynUuZ3C-JHHImuYriFPKXMTW3eQ7d341AGn40TrzLUJBRAiFL_yWlfhW4o7beRlAi9TKJxl7Uo6GwIlTHRW21RR4Umtgk&node=1i204",
              "etag": "0eSNGimACUM+JKU1TGqgZRw=="
            },
            {
              "w": 720,
              "h": 306,
              "size": "504",
              "url": "/sapi/download/video?action=get&k=n6Ca8NU0_AP4NMVuTmI0pKFj6XSvjGsX40xY3HI72CsAWOV7M8LWOLw4ItaZqb05ENStnzVVbSM3YCTuv-wMEixMpsAA24N1jRe0FZyzcp6TjNlkbkEVdB8P_EdiEQR1NLLPUehesbokmkvG3WLovklTa2m7yOFQPV8GX_RXC4_KD02zCq3piTZLnl2sMrHkP88&node=1i204",
              "etag": "0eSNGimACUM+JKU1TGqgZRw=="
            }
          ],
          "mediatype": "video",
          "status": "U",
          "etag": "eSNGimACUM+JKU1TGqgZRw==",
          "favorite": false
        }
      ]
    },
    "responsetime": 1777835445253,
    "type": "video"
  },
  "share_url": "https://cloud.jazzdrive.com.pk/share/f/Bf5UACvgQH-HON7Qdv2gnDk3NTU1MTgzNjY3NzFfMjYxODU0Ng",
  "share_key": "",
  "share_folder_id": "",
  "share_folder_path": "Ki Mein Jhoot Boleya (2023)",
  "media_kind": "movie"
}