{
  "name": "\u0915\u094d\u092f\u093e \u0935\u093e\u0915\u0908 \u092a\u0930\u0947\u0936 \u0930\u093e\u0935\u0932 \u0928\u0947 \u0915\u093f\u092f\u093e \u092e\u093e\u0927\u0941\u0930\u0940 \u0915\u093e \u092c\u0932\u093e\u0924\u094d\u0915\u093e\u0930- - Madhuri - Sanjay Kapoor - Paresh Rawal -Full Movie.mp4",
  "path": "K:\\All MOVIES\\Hindi Film\\tiger sheroff7\\\u0915\u094d\u092f\u093e \u0935\u093e\u0915\u0908 \u092a\u0930\u0947\u0936 \u0930\u093e\u0935\u0932 \u0928\u0947 \u0915\u093f\u092f\u093e \u092e\u093e\u0927\u0941\u0930\u0940 \u0915\u093e \u092c\u0932\u093e\u0924\u094d\u0915\u093e\u0930- - Madhuri - Sanjay Kapoor - Paresh Rawal -Full Movie.mp4",
  "uploaded_at": "2026-05-03T14:23:58Z",
  "remote_folder_id": 1753417,
  "mediatype": "video",
  "stream_link": "https://cloud.jazzdrive.com.pk/ui/html/video.html?id=242121708",
  "tmdb": null,
  "response": {
    "success": "Media uploaded successfully",
    "id": "242121708",
    "status": "U",
    "etag": "mvkJ2LsUH2YanvOW5sMOqQ==",
    "metadata": {
      "mediaserverurl": "https://cloud.jazzdrive.com.pk",
      "videos": [
        {
          "id": "242121708",
          "url": "/sapi/download/video?action=get&k=_nKkDxmfsH2MUzkn6XCCw65qzxn54qWzNgqsrUNPJzlwtrdeAIDUlkJkO2tN9W3_xk2vxLPDMh_em7RKCN7fKOlNM7Hrmkfzrd_Zjj4mG6oY5PQlxpiSPvOAAMV2hkefWeGGcFwlwpyWSxNrFbVSq0T9gvF9Wz0v63pLr18i4vIYThvR17s&node=1i204",
          "viewurl": "/sapi/download/video?action=get&k=MpqA5QSULjoIE17FlTm1-ot6d-WNNYWp2Sa1JVORT19TKvVCsTxUGNz2pHOL2J0Vs7YCATtx96TkhOj3GwcEHMokbwbKN4jEK_eTh-Ex42GG10D_6va08dTN2E71BYcNFsko3Co3HA1E42A8ERHYDQwJE3DdWykhZxLSTmXYsFwurniHNrtAckhhx9uvF7KLfwU&node=1i204",
          "date": 1777818236435,
          "creationdate": 1777817146000,
          "modificationdate": 1777817146000,
          "uploaded": 1777818214466,
          "size": 733948387,
          "name": "\u0915\u094d\u092f\u093e \u0935\u093e\u0915\u0908 \u092a\u0930\u0947\u0936 \u0930\u093e\u0935\u0932 \u0928\u0947 \u0915\u093f\u092f\u093e \u092e\u093e\u0927\u0941\u0930\u0940 \u0915\u093e \u092c\u0932\u093e\u0924\u094d\u0915\u093e\u0930- - Madhuri - Sanjay Kapoor - Paresh Rawal -Full Movie.mp4",
          "metadata": {
            "duration": 9390196,
            "bitrate": 625289,
            "codec": "h264",
            "height": 720,
            "width": 1280,
            "audiocodec": "aac"
          },
          "playbackurl": "",
          "transcodingstatus": "E",
          "thumbnails": [
            {
              "w": 256,
              "h": 144,
              "size": "176",
              "url": "/sapi/download/video?action=get&k=dgSmpLeelLCDxUGdvgJP5YowBv9-GlWoyzkSx1kFwUrjCUiBMs9MpYchRCSAn8vBWB-QXq3mGLXQjR5KSSYX-6kuLCrjImRySmRVhy1lB5sxhGOpk76odXdZ_LYJajuRGPAB5MZehSNlroZgJnj1iKRSNsCWd2KnNXnTZN3ESXK_UqkSWlDrAHgtd0WJoYe92yQ&node=1i204",
              "etag": "0mvkJ2LsUH2YanvOW5sMOqQ=="
            },
            {
              "w": 1024,
              "h": 576,
              "size": "504",
              "url": "/sapi/download/video?action=get&k=MpqA5QSULjoIE17FlTm1-ot6d-WNNYWp2Sa1JVORT19TKvVCsTxUGNz2pHOL2J0Vs7YCATtx96TkhOj3GwcEHMokbwbKN4jEK_eTh-Ex42GG10D_6va08dTN2E71BYcNFsko3Co3HA1E42A8ERHYDQwJE3DdWykhZxLSTmXYsFwurniHNrtAckhhx9uvF7KLfwU&node=1i204",
              "etag": "0mvkJ2LsUH2YanvOW5sMOqQ=="
            }
          ],
          "mediatype": "video",
          "status": "U",
          "etag": "mvkJ2LsUH2YanvOW5sMOqQ==",
          "favorite": false
        }
      ]
    },
    "responsetime": 1777818236509,
    "type": "video"
  },
  "share_url": "https://cloud.jazzdrive.com.pk/share/f/LhZYQfcbRXy8MAe37AWZFDk3NTU1MTgzNjY3NzFfMjYxODU0Ng",
  "share_key": "",
  "share_folder_id": "",
  "share_folder_path": "Madhuri Sanjay Kapoor Paresh Rawal Full Movie",
  "media_kind": "file"
}